{
  "parent": "minecraft:recipes/root",
  "criteria": {
    "has_mournful_primordite_block": {
      "conditions": {
        "items": [
          {
            "items": [
              "primanomalies:mournful_primordite_block"
            ]
          }
        ]
      },
      "trigger": "minecraft:inventory_changed"
    },
    "has_the_recipe": {
      "conditions": {
        "recipe": "primanomalies:mournful_primordite"
      },
      "trigger": "minecraft:recipe_unlocked"
    }
  },
  "requirements": [
    [
      "has_mournful_primordite_block",
      "has_the_recipe"
    ]
  ],
  "rewards": {
    "recipes": [
      "primanomalies:mournful_primordite"
    ]
  },
  "sends_telemetry_event": false
}